pi_tokenize-0.0.1.dist-info/RECORD
pi_tokenize-0.0.1.dist-info/WHEEL
pi_tokenize-0.0.1.dist-info/top_level.txt
pi_tokenize-0.0.1.dist-info/METADATA
pi_tokenize/token.py
pi_tokenize/__init__.py
pi_tokenize/_tokenize.py
pi_tokenize/tokenize.py
pi_tokenize/_vendor/__init__.py
pi_tokenize/_vendor/cpython/token.py
pi_tokenize/_vendor/cpython/__init__.py
pi_tokenize/_vendor/cpython/tokenize.py
pi_tokenize/_vendor/cpython/_tokenize/errcode.h
pi_tokenize/_vendor/cpython/_tokenize/compat.c
pi_tokenize/_vendor/cpython/_tokenize/pycore_token.h
pi_tokenize/_vendor/cpython/_tokenize/module.c
pi_tokenize/_vendor/cpython/_tokenize/token.c
pi_tokenize/_vendor/cpython/_tokenize/pythoncapi_compat.h
pi_tokenize/_vendor/cpython/_tokenize/__init__.py
pi_tokenize/_vendor/cpython/_tokenize/compat.h
pi_tokenize/_vendor/cpython/_tokenize/_tokenize.cpython-314-darwin.so
pi_tokenize/_vendor/cpython/_tokenize/lexer/buffer.c
pi_tokenize/_vendor/cpython/_tokenize/lexer/state.c
pi_tokenize/_vendor/cpython/_tokenize/lexer/lexer.c
pi_tokenize/_vendor/cpython/_tokenize/lexer/buffer.h
pi_tokenize/_vendor/cpython/_tokenize/lexer/lexer.h
pi_tokenize/_vendor/cpython/_tokenize/lexer/state.h
pi_tokenize/_vendor/cpython/_tokenize/tokenizer/utf8_tokenizer.c
pi_tokenize/_vendor/cpython/_tokenize/tokenizer/file_tokenizer.c
pi_tokenize/_vendor/cpython/_tokenize/tokenizer/tokenizer.h
pi_tokenize/_vendor/cpython/_tokenize/tokenizer/helpers.c
pi_tokenize/_vendor/cpython/_tokenize/tokenizer/helpers.h
pi_tokenize/_vendor/cpython/_tokenize/tokenizer/string_tokenizer.c
pi_tokenize/_vendor/cpython/_tokenize/tokenizer/readline_tokenizer.c
